[
    [
        {
            "setting": "故事发生在一个古老的帝国，这是一个神话和现实交织的世界，古老的神祇与人类共享这片土地。这个帝国被称为‘煌黎帝国’，历史悠久，文化底蕴深厚。",
            "plot": "故事的主角名叫‘辛弘’，他是一个普通的农民，每天辛勤耕作，过着平淡无奇的生活。然而，一天，他在田里挖到了一块神秘的石头，从此他的生活发生了翻天覆地的变化。",
            "characters_dict": {
                "辛弘": "故事的主角，原本是一个普通的农民，后来被赋予神的力量。",
                "煌黎帝国皇帝": "一个威严而又深思熟虑的君主，他对辛弘的出现充满了警惕。",
                "神祇": "赋予辛弘力量的神，他们有自己的目的。",
                "村长": "辛弘的朋友和导师，他对辛弘的变化感到惊讶。",
                "村民们": "对辛弘的变化持有各种态度的村民们。"
            }
        },
        {
            "setting": "辛弘的田间小屋，夜晚，村民们围坐炉火旁，听他讲述神赐力量的故事。",
            "plot": "辛弘在村民们的见证下，讲述了他如何在神秘石头中发现神力的觉醒过程，以及他在神祇的引导下逐渐理解并控制这种力量的经历。村民们开始反思自己对力量的理解，形成了一种集体学习和成长的氛围。",
            "characters_dict": {
                "- 辛弘": "在村民面前，他不再是单纯的农民，而是作为一个引导者，教导他们如何正确面对和使用潜在的力量。",
                "- 村民们": "他们开始质疑自己对力量的传统观念，积极参与到自我认知和力量掌控的学习中。",
                "- 神祇": "作为隐形的存在，他们通过辛弘传达信息，引导村民们理解力量的真正含义。",
                "- 辛弘的父亲": "作为村里的长者，他开始担忧儿子的力量可能会带来的危险，但在理解后成为支持辛弘的重要角色。",
                "- 村长": "他不仅是辛弘的朋友，也是力量教育的积极推动者，鼓励村民们相信自己，同时帮助辛弘建立责任感。",
                "在皇宫": "",
                "[setting]": "煌黎帝国皇宫，辛弘独自面对皇帝，他带来了关于村民学习和成长的进展，以及他关于力量平衡的深思。",
                "[plot]": "辛弘提出关于力量道德教育的计划，希望得到皇室的支持，让整个帝国的人都能明白力量的真正价值。皇帝深受触动，决定给予辛弘指导，共同推动帝国的变革。"
            }
        },
        {
            "setting": "故事的结尾发生在煌黎帝国的皇宫，这是一个金碧辉煌的地方，充满了权力和荣耀。",
            "plot": "辛弘经历了一系列的挑战和考验，他的力量越来越强大，最终他成为了能够决定帝国命运的英雄。他用自己的力量保护了煌黎帝国，使其免于灾难。",
            "characters_dict": {
                "辛弘": "现在的他已经不再是一个普通的农民，而是一个拥有神的力量的英雄。",
                "煌黎帝国皇帝": "他对辛弘的力量表示尊重，并感谢他救了煌黎帝国。",
                "神祇": "他们对辛弘的成长感到满意，认为他是一个值得信赖的人。",
                "村长": "他为辛弘的成就感到骄傲，他知道辛弘会保护他们的家乡。",
                "村民们": "他们对辛弘的敬仰之情溢于言表，他们感谢他为村庄所做的一切。"
            }
        }
    ],
    [
        {
            "setting": "辛弘在煌黎帝国的古老农田，阳光透过树叶洒下，金色的麦浪随风起伏。",
            "plot": "辛弘在日常劳作时无意发现神秘石头，这块石头散发出奇异的光芒，吸引了他的注意。他好奇地挖掘，意外触发了石头的神秘力量。",
            "characters_dict": {
                "辛弘": "故事主角，朴实的农民，对未知的好奇心驱使他揭开神秘面纱。",
                "煌黎帝国皇帝": "背景角色，对辛弘的异变保持着谨慎的态度。",
                "村长": "辛弘的邻居和朋友，对辛弘的发现感到震惊，成为他的初步支持者。",
                "村民们": "村民们的反应各异，有的人恐惧，有的人好奇，形成故事的冲突点。"
            }
        },
        {
            "setting": "辛弘的田间小屋，夜晚，炉火熊熊，村民们围坐聆听。",
            "plot": "辛弘坐在火堆旁，讲述他在田间劳作时偶然发现神秘石头的经过，他如何在石头中感受到一股奇异的能量，随后开始体验到神力的觉醒。",
            "characters_dict": {}
        },
        {
            "setting": "村民们的小屋后院，月光洒落，众人围坐讨论。",
            "plot": "村民们围绕着辛弘，分享自己的感受，开始探讨力量的意义和责任，彼此之间的关系变得更加紧密。",
            "characters_dict": {}
        },
        {
            "setting": "辛弘的父亲的旧书房，夜晚，父亲面带忧虑。",
            "plot": "辛弘的父亲担心儿子的力量可能带来的后果，但他看到儿子的成长和村民的变化，开始理解并接纳这个变化。",
            "characters_dict": {}
        },
        {
            "setting": "村长的家中，深夜，两人秘密交谈。",
            "plot": "村长赞同辛弘的想法，并承诺提供资源，他希望辛弘的力量能引领村民走向更美好的未来。",
            "characters_dict": {}
        },
        {
            "setting": "煌黎帝国皇宫，辛弘单独晋见皇帝。",
            "plot": "辛弘带着村庄的经验和教训，向皇帝阐述了力量教育的重要性，请求皇室的支持和指导。",
            "characters_dict": {}
        },
        {
            "setting": "煌黎帝国皇宫的金色大殿，富丽堂皇的装饰反射着太阳的光芒，象征着权力和威严。",
            "plot": "辛弘在大殿上接受皇帝的加冕，他的英勇事迹和力量得到了煌黎帝国的认可。他站在万人瞩目的舞台上，决定性的时刻来临。",
            "characters_dict": {
                "辛弘": "成长为英雄的农夫，拥有强大的力量，肩负起守护国家的使命。",
                "煌黎帝国皇帝": "身份高贵，对辛弘的英勇和忠诚充满敬意，象征着帝国的权威。",
                "神祇": "在云端默默注视，他们的认可推动了辛弘的成长，期待他成为真正的守护者。",
                "村长": "面带微笑，眼中闪烁着自豪，辛弘的成功是他村民的骄傲，也是他们信念的见证。",
                "村民们": "站在大殿外欢呼雀跃，他们的敬仰和感激化为热烈的掌声，辛弘的胜利是他们的希望和荣光。"
            }
        }
    ]
]